[
    {
    "textComponentId": 1,
    "name": "capitalise proper noun",
    "example": "This ia a placeholder example for Capitalise Proper Noun",
    "markupId": 1,
    "flag": {
    "flagId": 10,
    "name": "Correct",
    "colour": "green",
    "characters": null
    }
    },
    {
    "textComponentId": 1,
    "name": "capitalise proper noun",
    "example": "This ia a placeholder example for Capitalise Proper Noun",
    "markupId": 1,
    "flag": {
    "flagId": 11,
    "name": "Incorrect",
    "colour": "red",
    "characters": null
    }
    },
    {
    "textComponentId": 2,
    "name": "capitalise key event",
    "example": "This ia a placeholder example for Capitalise Key Event",
    "markupId": 1,
    "flag": {
    "flagId": 10,
    "name": "Correct",
    "colour": "green",
    "characters": null
    }
    },
    {
    "textComponentId": 2,
    "name": "capitalise key event",
    "example": "This ia a placeholder example for Capitalise Key Event",
    "markupId": 1,
    "flag": {
    "flagId": 11,
    "name": "Incorrect",
    "colour": "red",
    "characters": null
    }
    },
    {
    "textComponentId": 3,
    "name": "possessive apostrophie",
    "example": "This ia a placeholder example for Possessive Apostrophe",
    "markupId": 1,
    "flag": {
    "flagId": 10,
    "name": "Correct",
    "colour": "green",
    "characters": null
    }
    },
    {
    "textComponentId": 3,
    "name": "possessive apostrophie",
    "example": "This ia a placeholder example for Possessive Apostrophe",
    "markupId": 1,
    "flag": {
    "flagId": 11,
    "name": "Incorrect",
    "colour": "red",
    "characters": null
    }
    },
    {
    "textComponentId": 4,
    "name": "sentence boundary punct.",
    "example": "This ia a placeholder example for Sentence Boundary Punctuation",
    "markupId": 1,
    "flag": {
    "flagId": 10,
    "name": "Correct",
    "colour": "green",
    "characters": null
    }
    },
    {
    "textComponentId": 4,
    "name": "sentence boundary punct.",
    "example": "This ia a placeholder example for Sentence Boundary Punctuation",
    "markupId": 1,
    "flag": {
    "flagId": 11,
    "name": "Incorrect",
    "colour": "red",
    "characters": null
    }
    },
    {
    "textComponentId": 5,
    "name": "commas - lists",
    "example": "This ia a placeholder example for Commas - lists",
    "markupId": 1,
    "flag": {
    "flagId": 10,
    "name": "Correct",
    "colour": "green",
    "characters": null
    }
    },
    {
    "textComponentId": 5,
    "name": "commas - lists",
    "example": "This ia a placeholder example for Commas - lists",
    "markupId": 1,
    "flag": {
    "flagId": 11,
    "name": "Incorrect",
    "colour": "red",
    "characters": null
    }
    },
    {
    "textComponentId": 6,
    "name": "commas - dates",
    "example": "This ia a placeholder example for Commas - dates",
    "markupId": 1,
    "flag": {
    "flagId": 10,
    "name": "Correct",
    "colour": "green",
    "characters": null
    }
    },
    {
    "textComponentId": 6,
    "name": "commas - dates",
    "example": "This ia a placeholder example for Commas - dates",
    "markupId": 1,
    "flag": {
    "flagId": 11,
    "name": "Incorrect",
    "colour": "red",
    "characters": null
    }
    },
    {
    "textComponentId": 7,
    "name": "commas - pauses",
    "example": "This ia a placeholder example for Commas - pauses",
    "markupId": 1,
    "flag": {
    "flagId": 10,
    "name": "Correct",
    "colour": "green",
    "characters": null
    }
    },
    {
    "textComponentId": 7,
    "name": "commas - pauses",
    "example": "This ia a placeholder example for Commas - pauses",
    "markupId": 1,
    "flag": {
    "flagId": 11,
    "name": "Incorrect",
    "colour": "red",
    "characters": null
    }
    },
    {
    "textComponentId": 8,
    "name": "commas - quotes",
    "example": "This ia a placeholder example for Commas - quotes",
    "markupId": 1,
    "flag": {
    "flagId": 10,
    "name": "Correct",
    "colour": "green",
    "characters": null
    }
    },
    {
    "textComponentId": 8,
    "name": "commas - quotes",
    "example": "This ia a placeholder example for Commas - quotes",
    "markupId": 1,
    "flag": {
    "flagId": 11,
    "name": "Incorrect",
    "colour": "red",
    "characters": null
    }
    },
    {
    "textComponentId": 9,
    "name": "quotes for dialogue",
    "example": "This ia a placeholder example for Quotes for Dialigue",
    "markupId": 1,
    "flag": {
    "flagId": 10,
    "name": "Correct",
    "colour": "green",
    "characters": null
    }
    },
    {
    "textComponentId": 9,
    "name": "quotes for dialogue",
    "example": "This ia a placeholder example for Quotes for Dialigue",
    "markupId": 1,
    "flag": {
    "flagId": 11,
    "name": "Incorrect",
    "colour": "red",
    "characters": null
    }
    },
    {
    "textComponentId": 10,
    "name": "commas - separate clauses",
    "example": "This ia a placeholder example for Commas - separate clauses",
    "markupId": 1,
    "flag": {
    "flagId": 10,
    "name": "Correct",
    "colour": "green",
    "characters": null
    }
    },
    {
    "textComponentId": 10,
    "name": "commas - separate clauses",
    "example": "This ia a placeholder example for Commas - separate clauses",
    "markupId": 1,
    "flag": {
    "flagId": 11,
    "name": "Incorrect",
    "colour": "red",
    "characters": null
    }
    },
    {
    "textComponentId": 13,
    "name": "simple punctuation",
    "example": "This ia a placeholder example for Simple Punctuation",
    "markupId": 1,
    "flag": {
    "flagId": 10,
    "name": "Correct",
    "colour": "green",
    "characters": null
    }
    },
    {
    "textComponentId": 13,
    "name": "simple punctuation",
    "example": "This ia a placeholder example for Simple Punctuation",
    "markupId": 1,
    "flag": {
    "flagId": 11,
    "name": "Incorrect",
    "colour": "red",
    "characters": null
    }
    },
    {
    "textComponentId": 14,
    "name": "complex punctuation",
    "example": "This ia a placeholder example for Complex Punctuation",
    "markupId": 1,
    "flag": {
    "flagId": 10,
    "name": "Correct",
    "colour": "green",
    "characters": null
    }
    },
    {
    "textComponentId": 14,
    "name": "complex punctuation",
    "example": "This ia a placeholder example for Complex Punctuation",
    "markupId": 1,
    "flag": {
    "flagId": 11,
    "name": "Incorrect",
    "colour": "red",
    "characters": null
    }
    }
    ]